optuna_integration/__init__.py
optuna_integration/_imports.py
optuna_integration/version.py
optuna_integration/allennlp/__init__.py
optuna_integration/allennlp/_dump_best_config.py
optuna_integration/allennlp/_environment.py
optuna_integration/allennlp/_executor.py
optuna_integration/allennlp/_pruner.py
optuna_integration/allennlp/_variables.py
optuna_integration/botorch/__init__.py
optuna_integration/botorch/botorch.py
optuna_integration/catboost/__init__.py
optuna_integration/catboost/catboost.py
optuna_integration/chainer/__init__.py
optuna_integration/chainer/chainer.py
optuna_integration/chainermn/__init__.py
optuna_integration/chainermn/chainermn.py
optuna_integration/cma/__init__.py
optuna_integration/cma/cma.py
optuna_integration/comet/__init__.py
optuna_integration/comet/comet.py
optuna_integration/dask/__init__.py
optuna_integration/dask/dask.py
optuna_integration/fastaiv2/__init__.py
optuna_integration/fastaiv2/fastaiv2.py
optuna_integration/keras/__init__.py
optuna_integration/keras/keras.py
optuna_integration/lightgbm/__init__.py
optuna_integration/lightgbm/lightgbm.py
optuna_integration/lightgbm/_lightgbm_tuner/__init__.py
optuna_integration/lightgbm/_lightgbm_tuner/_train.py
optuna_integration/lightgbm/_lightgbm_tuner/alias.py
optuna_integration/lightgbm/_lightgbm_tuner/optimize.py
optuna_integration/lightgbm/_lightgbm_tuner/sklearn.py
optuna_integration/mlflow/__init__.py
optuna_integration/mlflow/mlflow.py
optuna_integration/mxnet/__init__.py
optuna_integration/mxnet/mxnet.py
optuna_integration/pytorch_distributed/__init__.py
optuna_integration/pytorch_distributed/pytorch_distributed.py
optuna_integration/pytorch_ignite/__init__.py
optuna_integration/pytorch_ignite/pytorch_ignite.py
optuna_integration/pytorch_lightning/__init__.py
optuna_integration/pytorch_lightning/pytorch_lightning.py
optuna_integration/shap/__init__.py
optuna_integration/shap/shap.py
optuna_integration/sklearn/__init__.py
optuna_integration/sklearn/sklearn.py
optuna_integration-4.7.0.dist-info/licenses/LICENSE
optuna_integration-4.7.0.dist-info/METADATA
optuna_integration-4.7.0.dist-info/WHEEL
optuna_integration-4.7.0.dist-info/top_level.txt
optuna_integration-4.7.0.dist-info/RECORD
