Metadata-Version: 2.4
Name: optuna-integration
Version: 4.7.0
Summary: Integration libraries of Optuna.
Project-URL: repository, https://github.com/optuna/optuna-integration
Classifier: Development Status :: 5 - Production/Stable
Classifier: Intended Audience :: Science/Research
Classifier: Intended Audience :: Developers
Classifier: License :: OSI Approved :: MIT License
Classifier: Programming Language :: Python :: 3
Classifier: Programming Language :: Python :: 3.9
Classifier: Programming Language :: Python :: 3.10
Classifier: Programming Language :: Python :: 3.11
Classifier: Programming Language :: Python :: 3.12
Classifier: Programming Language :: Python :: 3.13
Classifier: Programming Language :: Python :: 3 :: Only
Classifier: Topic :: Scientific/Engineering
Classifier: Topic :: Scientific/Engineering :: Mathematics
Classifier: Topic :: Scientific/Engineering :: Artificial Intelligence
Classifier: Topic :: Software Development
Classifier: Topic :: Software Development :: Libraries
Classifier: Topic :: Software Development :: Libraries :: Python Modules
Requires-Python: >=3.9
License-File: LICENSE
Requires-Dist: optuna
Provides-Extra: test
Requires-Dist: pytest; extra == "test"
Requires-Dist: coverage; extra == "test"
Requires-Dist: fakeredis[lua]; extra == "test"
Requires-Dist: grpcio; extra == "test"
Requires-Dist: protobuf>=5.28.1; extra == "test"
Provides-Extra: checking
Requires-Dist: black<25.9.0; extra == "checking"
Requires-Dist: blackdoc<0.4.2; extra == "checking"
Requires-Dist: hacking; extra == "checking"
Requires-Dist: isort; extra == "checking"
Requires-Dist: mypy; extra == "checking"
Requires-Dist: types-PyYAML; extra == "checking"
Requires-Dist: types-redis; extra == "checking"
Requires-Dist: types-setuptools; extra == "checking"
Requires-Dist: typing_extensions>=3.10.0.0; extra == "checking"
Provides-Extra: document
Requires-Dist: mlflow; extra == "document"
Requires-Dist: pandas; extra == "document"
Requires-Dist: scikit-learn>=0.24.2; extra == "document"
Requires-Dist: scipy>=1.9.2; python_version >= "3.9" and extra == "document"
Requires-Dist: sphinx; extra == "document"
Requires-Dist: sphinx-notfound-page; extra == "document"
Requires-Dist: sphinx_rtd_theme; extra == "document"
Provides-Extra: allennlp
Requires-Dist: allennlp; extra == "allennlp"
Requires-Dist: jsonnet; extra == "allennlp"
Requires-Dist: numpy<2.0.0; extra == "allennlp"
Requires-Dist: psutil; extra == "allennlp"
Provides-Extra: chainer
Requires-Dist: chainer; extra == "chainer"
Requires-Dist: numpy<2.0.0; extra == "chainer"
Provides-Extra: chainermn
Requires-Dist: chainermn; extra == "chainermn"
Requires-Dist: numpy<2.0.0; extra == "chainermn"
Provides-Extra: botorch
Requires-Dist: botorch<0.10.0; extra == "botorch"
Provides-Extra: catboost
Requires-Dist: numpy<2.0.0; extra == "catboost"
Requires-Dist: catboost; extra == "catboost"
Provides-Extra: cma
Requires-Dist: numpy<2.0.0; extra == "cma"
Requires-Dist: cma; extra == "cma"
Provides-Extra: comet
Requires-Dist: comet_ml>=3.39.3; extra == "comet"
Provides-Extra: dask
Requires-Dist: distributed; extra == "dask"
Provides-Extra: fastai
Requires-Dist: fastai>=2.0.0; extra == "fastai"
Provides-Extra: fastaiv2
Requires-Dist: fastai>=2.0.0; extra == "fastaiv2"
Provides-Extra: keras
Requires-Dist: tensorflow; extra == "keras"
Provides-Extra: lightgbm
Requires-Dist: lightgbm; extra == "lightgbm"
Requires-Dist: scikit-learn; extra == "lightgbm"
Provides-Extra: mlflow
Requires-Dist: mlflow; extra == "mlflow"
Provides-Extra: mxnet
Requires-Dist: mxnet; extra == "mxnet"
Provides-Extra: pytorch-distributed
Requires-Dist: gpytorch; extra == "pytorch-distributed"
Provides-Extra: pytorch-distributed
Requires-Dist: gpytorch; extra == "pytorch-distributed"
Provides-Extra: pytorch-ignite
Requires-Dist: pytorch-ignite; extra == "pytorch-ignite"
Provides-Extra: pytorch-ignite
Requires-Dist: pytorch-ignite; extra == "pytorch-ignite"
Provides-Extra: pytorch-lightning
Requires-Dist: lightning; extra == "pytorch-lightning"
Provides-Extra: pytorch-lightning
Requires-Dist: lightning; extra == "pytorch-lightning"
Provides-Extra: shap
Requires-Dist: numpy<2.0.0; extra == "shap"
Requires-Dist: shap; extra == "shap"
Provides-Extra: sklearn
Requires-Dist: pandas; extra == "sklearn"
Requires-Dist: scikit-learn; extra == "sklearn"
Requires-Dist: scipy; extra == "sklearn"
Provides-Extra: skorch
Requires-Dist: skorch; extra == "skorch"
Provides-Extra: tensorboard
Requires-Dist: tensorboard; extra == "tensorboard"
Requires-Dist: tensorflow; extra == "tensorboard"
Provides-Extra: tensorflow
Requires-Dist: tensorflow<=2.15.0; extra == "tensorflow"
Provides-Extra: tfkeras
Requires-Dist: tensorflow; extra == "tfkeras"
Provides-Extra: wandb
Requires-Dist: wandb; extra == "wandb"
Provides-Extra: xgboost
Requires-Dist: xgboost; extra == "xgboost"
Dynamic: license-file
